pivol/__init__.py
pivol-0.1.0.dist-info/LICENSE
pivol-0.1.0.dist-info/METADATA
pivol-0.1.0.dist-info/WHEEL
pivol-0.1.0.dist-info/RECORD
